{
  "id": "47a3f5d0-1d3e-49cd-afff-ebcb785331f3",
  "prevId": "5f61e711-fa07-4104-bb2a-3fac0333be32",
  "version": "5",
  "dialect": "pg",
  "tables": {
    "embeddings": {
      "name": "embeddings",
      "schema": "",
      "columns": {
        "id": {
          "name": "id",
          "type": "uuid",
          "primaryKey": true,
          "notNull": true,
          "default": "gen_random_uuid()"
        },
        "content": {
          "name": "content",
          "type": "varchar",
          "primaryKey": false,
          "notNull": true
        },
        "embedding": {
          "name": "embedding",
          "type": "vector(1536)",
          "primaryKey": false,
          "notNull": true
        },
        "archived": {
          "name": "archived",
          "type": "boolean",
          "primaryKey": false,
          "notNull": true,
          "default": false
        }
      },
      "indexes": {},
      "foreignKeys": {},
      "compositePrimaryKeys": {},
      "uniqueConstraints": {}
    }
  },
  "enums": {},
  "schemas": {},
  "_meta": {
    "columns": {},
    "schemas": {},
    "tables": {}
  }
}